{
	"cmake" : 
	{
		"generator" : 
		{
			"multiConfig" : false,
			"name" : "Unix Makefiles"
		},
		"paths" : 
		{
			"cmake" : "/usr/bin/cmake",
			"cpack" : "/usr/bin/cpack",
			"ctest" : "/usr/bin/ctest",
			"root" : "/usr/share/cmake-4.2"
		},
		"version" : 
		{
			"isDirty" : false,
			"major" : 4,
			"minor" : 2,
			"patch" : 1,
			"string" : "4.2.1",
			"suffix" : ""
		}
	},
	"objects" : 
	[
		{
			"jsonFile" : "codemodel-v2-51b5d14824fdfaab225c.json",
			"kind" : "codemodel",
			"version" : 
			{
				"major" : 2,
				"minor" : 9
			}
		},
		{
			"jsonFile" : "cache-v2-1e35ef676bfbd483946a.json",
			"kind" : "cache",
			"version" : 
			{
				"major" : 2,
				"minor" : 0
			}
		},
		{
			"jsonFile" : "cmakeFiles-v1-ecd99da62717a26bdefd.json",
			"kind" : "cmakeFiles",
			"version" : 
			{
				"major" : 1,
				"minor" : 1
			}
		}
	],
	"reply" : 
	{
		"cache-v2" : 
		{
			"jsonFile" : "cache-v2-1e35ef676bfbd483946a.json",
			"kind" : "cache",
			"version" : 
			{
				"major" : 2,
				"minor" : 0
			}
		},
		"cmakeFiles-v1" : 
		{
			"jsonFile" : "cmakeFiles-v1-ecd99da62717a26bdefd.json",
			"kind" : "cmakeFiles",
			"version" : 
			{
				"major" : 1,
				"minor" : 1
			}
		},
		"codemodel-v2" : 
		{
			"jsonFile" : "codemodel-v2-51b5d14824fdfaab225c.json",
			"kind" : "codemodel",
			"version" : 
			{
				"major" : 2,
				"minor" : 9
			}
		}
	}
}
